iamunused/__init__.py
iamunused/__main__.py
iamunused/reader.py
iamunused/test_reader.py
iamunused-0.2.9.dist-info/LICENSE
iamunused-0.2.9.dist-info/METADATA
iamunused-0.2.9.dist-info/WHEEL
iamunused-0.2.9.dist-info/entry_points.txt
iamunused-0.2.9.dist-info/top_level.txt
iamunused-0.2.9.dist-info/RECORD
