Metadata-Version: 2.1
Name: iamunused
Version: 0.2.9
Summary: Scan and remediate unused permissions within IAM Policies
Home-page: https://github.com/chrisdunne/iamunused
Author: Chris Dunne
Author-email: contact@chrisdunne.net
License: MIT
Platform: UNKNOWN
Classifier: License :: OSI Approved :: MIT License
Classifier: Programming Language :: Python :: 3
Classifier: Programming Language :: Python :: 3.9
Requires-Dist: boto3
